LICENSE
README.rst
pyproject.toml
setup.py
homogeneous_transformation/__init__.py
homogeneous_transformation/quaternion.py
homogeneous_transformation/version.py
homogeneous_transformation.egg-info/PKG-INFO
homogeneous_transformation.egg-info/SOURCES.txt
homogeneous_transformation.egg-info/dependency_links.txt
homogeneous_transformation.egg-info/top_level.txt
homogeneous_transformation/merlict_c89/__init__.py
homogeneous_transformation/merlict_c89/chk_debug.c
homogeneous_transformation/merlict_c89/chk_debug.h
homogeneous_transformation/merlict_c89/gather_sources_from_merlict_c89.py
homogeneous_transformation/merlict_c89/loops.h
homogeneous_transformation/merlict_c89/mliHomTra.c
homogeneous_transformation/merlict_c89/mliHomTra.h
homogeneous_transformation/merlict_c89/mliMat.c
homogeneous_transformation/merlict_c89/mliMat.h
homogeneous_transformation/merlict_c89/mliQuaternion.c
homogeneous_transformation/merlict_c89/mliQuaternion.h
homogeneous_transformation/merlict_c89/mliRay.c
homogeneous_transformation/merlict_c89/mliRay.h
homogeneous_transformation/merlict_c89/mliVec.c
homogeneous_transformation/merlict_c89/mliVec.h
homogeneous_transformation/merlict_c89/mli_quadratic_equation.c
homogeneous_transformation/merlict_c89/mli_quadratic_equation.h
homogeneous_transformation/merlict_c89/mli_version.c
homogeneous_transformation/merlict_c89/mli_version.h
homogeneous_transformation/merlict_c89/wrapper.c
homogeneous_transformation/merlict_c89/wrapper.pyx