Metadata-Version: 2.1
Name: homogeneous-transformation
Version: 0.0.1.1.7.2
Summary: View and work on plenoscope events
Home-page: https://github.com/cherenkov-plenoscope/homogeneous_transformation
Author: Sebastian Achim Mueller
Author-email: sebastian-achim.mueller@mpi-hd.mpg.de
Classifier: Programming Language :: Python :: 3
Classifier: License :: OSI Approved :: GNU General Public License v3 (GPLv3)
Classifier: Operating System :: OS Independent
Classifier: Natural Language :: English
Classifier: Intended Audience :: Science/Research
License-File: LICENSE
